cassandra_asyncio/__init__.py
cassandra_asyncio/cluster.py
cassandra_asyncio/version.py
cassandra_asyncio_driver-0.1.4.dist-info/METADATA
cassandra_asyncio_driver-0.1.4.dist-info/WHEEL
cassandra_asyncio_driver-0.1.4.dist-info/entry_points.txt
cassandra_asyncio_driver-0.1.4.dist-info/licenses/LICENSE
cassandra_asyncio_driver-0.1.4.dist-info/RECORD
