Metadata-Version: 2.1
Name: cassandra-asyncio-driver
Version: 0.1.4
Summary: Wrapper for cassandra-driver that makes queries awaitable using asyncio
Author-Email: Mark Parncutt <me@markparncutt.com>
License: MIT
Requires-Python: >=3.8
Requires-Dist: cassandra-driver>=3.29.2
